README.md
setup.py
ml_scrapy/__init__.py
ml_scrapy.egg-info/PKG-INFO
ml_scrapy.egg-info/SOURCES.txt
ml_scrapy.egg-info/dependency_links.txt
ml_scrapy.egg-info/top_level.txt
ml_scrapy/middlewares/__init__.py
ml_scrapy/middlewares/ua/__init__.py
ml_scrapy/middlewares/ua/ua_list.py
ml_scrapy/middlewares/ua/useragent.py