Metadata-Version: 2.1
Name: ml-scrapy
Version: 0.0.4
Summary: Components For Scrapy Project
Home-page: https://github.com/mic1on/ml-scrapy
Author: miclon
Author-email: jcnd@163.com
License: MIT Licence
Keywords: pip,scrapy
Platform: any
